btypes/__init__.py
btypes/_types.py
btypes/py.typed
btypes-4.1.1.dist-info/LICENSE
btypes-4.1.1.dist-info/WHEEL
btypes-4.1.1.dist-info/METADATA
btypes-4.1.1.dist-info/RECORD
