Metadata-Version: 2.1
Name: btypes
Version: 4.1.1
Summary: Aliases with correct capitalization for built-in Python types.
Home-page: https://github.com/thomkeh/btypes
License: Apache 2.0
Author: Thomas M
Author-email: thomas5max@gmail.com
Requires-Python: >=3.9,<4.0
Classifier: License :: OSI Approved :: Apache Software License
Classifier: License :: Other/Proprietary License
Classifier: Operating System :: OS Independent
Classifier: Programming Language :: Python :: 3
Classifier: Programming Language :: Python :: 3.10
Classifier: Programming Language :: Python :: 3.9
Classifier: Typing :: Typed
Requires-Dist: typing-extensions (==4.1.1)
Project-URL: Repository, https://github.com/thomkeh/btypes
